easysh/__init__.py
easysh/shell.py
easysh/shell_command.py
easysh/shell_error.py
easysh-1.0.0.dist-info/LICENSE
easysh-1.0.0.dist-info/METADATA
easysh-1.0.0.dist-info/WHEEL
easysh-1.0.0.dist-info/top_level.txt
easysh-1.0.0.dist-info/RECORD
