Metadata-Version: 2.1
Name: easysh
Version: 1.0.0
Summary: an easy to execute shell commands in Python.
Home-page: https://github.com/yingjiaxin/easysh
Author: vince
Author-email: yingjiaxin202@163.com
License: MIT
Keywords: shell sh
Platform: UNKNOWN
Classifier: Development Status :: 5 - Production/Stable
Classifier: Intended Audience :: Developers
Classifier: License :: OSI Approved :: MIT License
Classifier: Operating System :: OS Independent
Classifier: Programming Language :: Python
Classifier: Topic :: System :: Shells
Classifier: Topic :: Utilities
Classifier: Programming Language :: Python :: 3
Requires-Dist: chardet
